adataset/__init__.py
adataset/main.py
adataset/calibration_meta/camera_params/camera_extrinsics.yaml
adataset/calibration_meta/camera_params/camera_intrinsics.yaml
adataset/calibration_meta/gnss_params/ant_imu_leverarm.yaml
adataset/calibration_meta/radar_params/radar_extrinsics.yaml
adataset/calibration_meta/vehicle_params/vehicle_imu_extrinsics.yaml
adataset/calibration_meta/velodyne_params/lidar_height.yaml
adataset/calibration_meta/velodyne_params/lidar_novatel_extrinsics.yaml
adataset/kitti/__init__.py
adataset/kitti/calibration_converter.py
adataset/kitti/common.py
adataset/kitti/dataset_converter.py
adataset/kitti/geometry.py
adataset/kitti/kitti.py
adataset/kitti/pcd_converter.py
adataset/kitti/proj_helper.py
adataset/kitti/sensor.py
adataset/nuscenes/__init__.py
adataset/nuscenes/calibration_converter.py
adataset/nuscenes/dataset_converter.py
adataset/nuscenes/geometry.py
adataset/nuscenes/nuscenes.py
adataset/nuscenes/pcd_converter.py
adataset-0.1.0.dist-info/METADATA
adataset-0.1.0.dist-info/WHEEL
adataset-0.1.0.dist-info/entry_points.txt
adataset-0.1.0.dist-info/top_level.txt
adataset-0.1.0.dist-info/RECORD
