Metadata-Version: 2.1
Name: adataset
Version: 0.1.0
Summary: Dataset conversion to Apollo record tool
Home-page: https://github.com/ApolloAuto/apollo/tree/master/modules/tools/adataset
Author: apollo-team
Author-email: apollo-support@baidu.com
Project-URL: Bug Tracker, https://github.com/ApolloAuto/apollo/issues
Classifier: Programming Language :: Python :: 3
Classifier: License :: OSI Approved :: Apache Software License
Classifier: Operating System :: OS Independent
Requires-Python: >=3.6
Requires-Dist: numpy
Requires-Dist: pyproj
Requires-Dist: cyber-record
Requires-Dist: record-msg
